odoo9_addon_base_import_async-9.0.1.1.0-py2.7-nspkg.pth
odoo_addons/base_import_async/__openerp__.py
odoo_addons/base_import_async/__init__.py
odoo_addons/base_import_async/README.rst
odoo_addons/base_import_async/models/base_import_async.py
odoo_addons/base_import_async/models/__init__.py
odoo_addons/base_import_async/views/base_import_async.xml
odoo_addons/base_import_async/static/src/js/import.js
odoo_addons/base_import_async/static/src/xml/import.xml
odoo9_addon_base_import_async-9.0.1.1.0.dist-info/top_level.txt
odoo9_addon_base_import_async-9.0.1.1.0.dist-info/WHEEL
odoo9_addon_base_import_async-9.0.1.1.0.dist-info/RECORD
odoo9_addon_base_import_async-9.0.1.1.0.dist-info/metadata.json
odoo9_addon_base_import_async-9.0.1.1.0.dist-info/DESCRIPTION.rst
odoo9_addon_base_import_async-9.0.1.1.0.dist-info/METADATA
odoo9_addon_base_import_async-9.0.1.1.0.dist-info/namespace_packages.txt
